audobject/__init__.py
audobject/core/__init__.py
audobject/core/api.py
audobject/core/config.py
audobject/core/decorator.py
audobject/core/define.py
audobject/core/dictionary.py
audobject/core/object.py
audobject/core/parameter.py
audobject/core/resolver.py
audobject/core/testing.py
audobject/core/utils.py
audobject/define/__init__.py
audobject/resolver/__init__.py
audobject/testing/__init__.py
docs/changelog.rst
docs/conf.py
docs/contributing.rst
docs/genindex.rst
docs/index.rst
docs/install.rst
docs/requirements.txt
docs/usage.rst
docs/_templates/autosummary/base.rst
docs/_templates/autosummary/class.rst
docs/_templates/autosummary/function.rst
docs/api-src/audobject.define.rst
docs/api-src/audobject.resolver.rst
docs/api-src/audobject.rst
docs/api-src/audobject.testing.rst
docs/pics/graph.dot
tests/conftest.py
tests/requirements.txt
tests/test_dictionary.py
tests/test_install.py
tests/test_object.py
tests/test_parameters.py
tests/test_resolver.py
tests/test_warnings.py
audobject-0.7.11.dist-info/LICENSE
audobject-0.7.11.dist-info/METADATA
audobject-0.7.11.dist-info/WHEEL
audobject-0.7.11.dist-info/top_level.txt
audobject-0.7.11.dist-info/RECORD
