Metadata-Version: 2.1
Name: audobject
Version: 0.7.11
Summary: Generic object interface
Author-email: Hagen Wierstorf <hwierstorf@audeering.com>
License: Copyright (c) 2019-2020 audEERING GmbH. All rights reserved.
Project-URL: repository, https://github.com/audeering/audobject/
Project-URL: documentation, https://audeering.github.io/audobject/
Keywords: serialization,yaml
Classifier: Development Status :: 5 - Production/Stable
Classifier: Intended Audience :: Science/Research
Classifier: Intended Audience :: Developers
Classifier: License :: OSI Approved :: MIT License
Classifier: Operating System :: OS Independent
Classifier: Programming Language :: Python
Classifier: Programming Language :: Python :: 3
Classifier: Programming Language :: Python :: 3.8
Classifier: Programming Language :: Python :: 3.9
Classifier: Programming Language :: Python :: 3.10
Classifier: Programming Language :: Python :: 3.11
Classifier: Topic :: Scientific/Engineering
License-File: LICENSE
Requires-Dist: audeer>=1.18.0
Requires-Dist: importlib-metadata>=4.8.0
Requires-Dist: oyaml
Requires-Dist: packaging
